toolkit_cmm/__init__.py
toolkit_cmm/_version.py
toolkit_cmm/eprint.py
toolkit_cmm/helloworld.py
toolkit_cmm/logger.py
toolkit_cmm/md5.py
toolkit_cmm/path_helper.py
toolkit_cmm/py.typed
toolkit_cmm/scan_folder.py
toolkit_cmm/singleton.py
toolkit_cmm/url_helper.py
toolkit_cmm/video2thumbnails.py
toolkit_cmm/thirdparty/__init__.py
toolkit_cmm/thirdparty/cloudflarescrape.py
toolkit_cmm/thirdparty/user_agents.py
toolkit_cmm-0.0.1.9.dist-info/METADATA
toolkit_cmm-0.0.1.9.dist-info/WHEEL
toolkit_cmm-0.0.1.9.dist-info/licenses/LICENSE
toolkit_cmm-0.0.1.9.dist-info/RECORD
