Metadata-Version: 2.4
Name: toolkit_cmm
Version: 0.0.1.9
Summary: Toolkit for personal use
Author-email: cromarmot <yexiaorain@gmail.com>
License: MIT
License-File: LICENSE
Keywords: toolkit
Classifier: Development Status :: 3 - Alpha
Classifier: License :: OSI Approved :: MIT License
Classifier: Operating System :: Unix
Classifier: Topic :: Software Development :: Libraries :: Python Modules
Classifier: Topic :: Utilities
Requires-Python: >=3.8
Requires-Dist: brotli>=1.1.0
Provides-Extra: dev
Requires-Dist: mypy>=1.2.0; extra == 'dev'
Requires-Dist: pytest>=7.0.0; extra == 'dev'
Requires-Dist: ruff>=0.1.0; extra == 'dev'
Requires-Dist: sphinx>=7.0.0; extra == 'dev'
